[
  {
    "name": "Сырники из творога",
    "cookingTime": 30,
    "ingredients": [
      { "name": "Творог", "count": 350, "measure": "г." },
      { "name": "Куриное яйцо", "count": 2, "measure": "шт." },
      { "name": "Пшеничная мука", "count": 6, "measure": "ст.л." },
      { "name": "Сахар ", "count": 2, "measure": "ст.л." }
    ],
    "steps": {
      "1": "Смешайте весь творог с яйцами, сахаром и тщательно всё перемешайте",
      "2": "Всыпьте в творог муку и тщательно перемешайте",
      "3": "Поставьте сковороду на средний огонь и налейте в нее подсолнечное масло",
      "4": "Слепите несколько небольших шариков из получившейся творожной массы и положите их на тарелку. Затем по очереди обкатывайте творожные шарики в муке и выкладывайте на сковороду",
      "5": "Обжаривайте сырники 1–2 минуты до появления золотистой корочки. Затем переверните их на другую сторону и также обжарьте до золотистого состояния",
      "6": "Повторяйте, пока творог не закончится"
    }
  },
  {
    "name": "Салат из красной фасоли с творожным сыром, красным луком и сезонным салатом",
    "cookingTime": 7,
    "ingredients": [
      { "name": "Специи", "count": "по вкусу", "measure": "по вкусу" },
      { "name": "Консервированная фасоль", "count": 400, "measure": "г." },
      { "name": "Лимон ", "count": 1, "measure": "шт." },
      { "name": "Чеснок   ", "count": 2, "measure": "зуб." },
      { "name": "Оливковое масло", "count": 50, "measure": "мл." },
      { "name": "Рукола ", "count": 100, "measure": "г." },
      { "name": "Творожный сыр ", "count": 200, "measure": "г." },
      { "name": "Красный лук ", "count": 50, "measure": "г." }
    ],
    "steps": {
      "1": "Открыть две банки красной фасоли в собственном соку, слить сок и промыть фасоль холодной водой",
      "2": "Готовую фасоль смешать с мелко нарубленным красным луком, зеленью, давленым чесноком, оливковым маслом, лимонным соком и творожным сыром",
      "3": "Посолить, поперчить, дать продуктам две минуты притереться друг к другу и подавать к столу"
    }
  },
  {
    "name": "Чечевичный суп с мятой",
    "cookingTime": 30,
    "ingredients": [
      { "name": "Красная чечевица", "count": 150, "measure": "г." },
      { "name": "Репчатый лук", "count": 1, "measure": "гол." },
      { "name": "Морковь", "count": 1, "measure": "шт." },
      { "name": "Подсолнечное масло   ", "count": 30, "measure": "мл." },
      { "name": "Сливочное  масло", "count": 15, "measure": "г." },
      { "name": "Пшеничная мука ", "count": 30, "measure": "г." },
      { "name": "Специи", "count": "по вкусу", "measure": "по вкусу" },
      { "name": "Лимон ", "count": 0.5, "measure": "шт." },
      { "name": "Мята", "count": "по вкусу", "measure": "по вкусу" }
    ],
    "steps": {
      "1": "В небольшую кастрюлю налить литр воды и засыпать промытую чечевицу. Поставить кастрюлю на средний огонь",
      "2": "Натереть небольшую морковь на крупной терке, мелко нарезать лук. Как только чечевица начнет кипеть, надо убавить огонь, а затем долить еще 200 мл воды или бульона. Варить еще десять минут",
      "3": "Разогреть широкую плоскую сковороду, добавить туда подсолнечное и сливочное масло. Обжарить лук и морковь.",
      "4": "Добавить обжаренные овощи в кастрюлю, влить сливки. Взбить суп ручным блендером, чтобы он превратился в густое пюре. Суп можно подавать к столу"
    }
  },
  {
    "name": "Салат с креветками и кунжутом",
    "cookingTime": 20,
    "ingredients": [
      { "name": "Помидоры ", "count": 3, "measure": "шт." },
      { "name": "Королевские креветки", "count": 300, "measure": "г." },
      { "name": "Зеленый салат", "count": 1, "measure": "пуч." },
      { "name": "Огурцы ", "count": 2, "measure": "шт." },
      { "name": "Специи", "count": "по вкусу", "measure": "по вкусу" },
      { "name": "Майонез ", "count": "по вкусу", "measure": "по вкусу"  },
      { "name": "Кунжутные семечки ", "count": 3, "measure": "ст.л." }
    ],
    "steps": {
      "1": "Порезать овощи крупно, салат порвать на куски",
      "2": "Довести до кипения сильно соленую воду и добавить креветки. После кипения варить 5 минут",
      "3": "Очистить креветки от панциря",
      "4": "Смешать овощи и креветки",
      "5": "Посыпать кунжутными семечками и заправить майонезом"
    }
  },
  {
    "name": "Творожные пончики в сахарной пудре",
    "cookingTime": 40,
    "ingredients": [
      { "name": "Творог", "count": 250, "measure": "г." },
      { "name": "Куриное яйцо", "count": 3, "measure": "шт." },
      { "name": "Пшеничная мука", "count": 8, "measure": "ст.л." },
      { "name": "Сахар  ", "count": "по вкусу", "measure": "по вкусу" },
      { "name": "Оливковое масло", "count": "по вкусу", "measure": "по вкусу" },
      { "name": "Сода ", "count": 1.2, "measure": "ч.л."  },
      { "name": "Сахарная пудра", "count": "по вкусу", "measure": "по вкусу" }
    ],
    "steps": {
      "1": "В миске смешать творог, яйца, муку, сахар, соду и соль до однородной консистенции.",
      "2": "В небольшом сотейнике оливковое масло хорошо разогреть",
      "3": "При помощи чайной ложки или руками скатать из теста шарики, каждый размером чуть меньше грецкого ореха",
      "4": "Бросить пончики в кипящее масло и жарить на небольшом огне, постоянно переворачивая шумовкой",
      "5": "Готовые пончики выложить на бумажное полотенце и оставить на одну-две минуты — чтобы оно впитало лишнее масло. Подавать пончики горячими, выложив на блюдо и посыпав сахарной пудрой, смешанной с ванилином"
    }
  }
]